pinecone_plugins/assistant/__init__.py
pinecone_plugins/assistant/assistant/__init__.py
pinecone_plugins/assistant/assistant/assistant.py
pinecone_plugins/assistant/control/core/client/__init__.py
pinecone_plugins/assistant/control/core/client/api/__init__.py
pinecone_plugins/assistant/control/core/client/api/manage_assistants_api.py
pinecone_plugins/assistant/control/core/client/api_client.py
pinecone_plugins/assistant/control/core/client/apis/__init__.py
pinecone_plugins/assistant/control/core/client/configuration.py
pinecone_plugins/assistant/control/core/client/exceptions.py
pinecone_plugins/assistant/control/core/client/model/__init__.py
pinecone_plugins/assistant/control/core/client/model/assistant.py
pinecone_plugins/assistant/control/core/client/model/error_response.py
pinecone_plugins/assistant/control/core/client/model/error_response_error.py
pinecone_plugins/assistant/control/core/client/model/inline_object.py
pinecone_plugins/assistant/control/core/client/model/inline_object1.py
pinecone_plugins/assistant/control/core/client/model/inline_response200.py
pinecone_plugins/assistant/control/core/client/model/inline_response2001.py
pinecone_plugins/assistant/control/core/client/model_utils.py
pinecone_plugins/assistant/control/core/client/models/__init__.py
pinecone_plugins/assistant/control/core/client/rest.py
pinecone_plugins/assistant/data/core/client/__init__.py
pinecone_plugins/assistant/data/core/client/api/__init__.py
pinecone_plugins/assistant/data/core/client/api/manage_assistants_api.py
pinecone_plugins/assistant/data/core/client/api_client.py
pinecone_plugins/assistant/data/core/client/apis/__init__.py
pinecone_plugins/assistant/data/core/client/configuration.py
pinecone_plugins/assistant/data/core/client/exceptions.py
pinecone_plugins/assistant/data/core/client/model/__init__.py
pinecone_plugins/assistant/data/core/client/model/assistant_file_model.py
pinecone_plugins/assistant/data/core/client/model/chat_completion_model.py
pinecone_plugin_assistant-2.0.0.dist-info/LICENSE.txt
pinecone_plugin_assistant-2.0.0.dist-info/METADATA
pinecone_plugin_assistant-2.0.0.dist-info/WHEEL
pinecone_plugin_assistant-2.0.0.dist-info/RECORD
