Metadata-Version: 2.3
Name: pinecone-plugin-assistant
Version: 2.0.0
Summary: Assistant plugin for Pinecone SDK
License: Apache-2.0
Author: Pinecone Systems, Inc.
Author-email: support@pinecone.io
Requires-Python: >=3.9,<4.0
Classifier: License :: OSI Approved :: Apache Software License
Classifier: Programming Language :: Python :: 3
Classifier: Programming Language :: Python :: 3.9
Classifier: Programming Language :: Python :: 3.10
Classifier: Programming Language :: Python :: 3.11
Classifier: Programming Language :: Python :: 3.12
Classifier: Programming Language :: Python :: 3.13
Requires-Dist: packaging (>=24.2,<25.0)
Requires-Dist: requests (>=2.32.3,<3.0.0)
Project-URL: Documentation, https://pinecone.io/docs
Project-URL: Homepage, https://www.pinecone.io
